window_ops/__init__.py
window_ops/_modidx.py
window_ops/ewm.py
window_ops/expanding.py
window_ops/online.py
window_ops/rolling.py
window_ops/shift.py
window_ops/utils.py
window_ops-0.0.15.dist-info/LICENSE
window_ops-0.0.15.dist-info/METADATA
window_ops-0.0.15.dist-info/WHEEL
window_ops-0.0.15.dist-info/entry_points.txt
window_ops-0.0.15.dist-info/top_level.txt
window_ops-0.0.15.dist-info/RECORD
