Metadata-Version: 2.1
Name: window_ops
Version: 0.0.15
Summary: Implementations of window operations such as rolling and expanding.
Home-page: https://github.com/jmoralez/window_ops/tree/master/
Author: José Morales
Author-email: jmorales@grupoabraxas.com
License: Apache Software License 2.0
Keywords: rolling,expanding
Classifier: Development Status :: 3 - Alpha
Classifier: Intended Audience :: Developers
Classifier: Natural Language :: English
Classifier: Programming Language :: Python :: 3.6
Classifier: Programming Language :: Python :: 3.7
Classifier: Programming Language :: Python :: 3.8
Classifier: Programming Language :: Python :: 3.9
Classifier: Programming Language :: Python :: 3.10
Classifier: License :: OSI Approved :: Apache Software License
Requires-Python: >=3.6
License-File: LICENSE
Requires-Dist: numba
Requires-Dist: numpy
Provides-Extra: dev
Requires-Dist: pandas ; extra == 'dev'
